{
  "$schema": "../../schema.json",
  "name": "brazil-comedy",
  "description": "Brazilian comedy themed verbs",
  "author": "JJ",
  "github": "jurrejan",
  "config": {
    "showTurnDuration": false,
    "spinnerVerbs": {
      "mode": "replace",
      "verbs": [
        "I'm fazering um jeitinho",
        "I'm reclamaring do trânsito",
        "I'm dizering aí meu Deus",
        "I'm riring sem parar",
        "I'm fazering cara de novela",
        "I'm choraring no close",
        "I'm jogaring a culpa fora",
        "I'm entraring em modo drama",
        "I'm soltaring uma piada rápida",
        "I'm fazering um sketch absurdo",
        "I'm cortaring com ironia",
        "I'm fingiring ser sério",
        "I'm mandaring um meme",
        "I'm debatering nos comentários",
        "I'm dizering é sobre isso",
        "I'm fazering textão curto",
        "I'm gritaring gol do nada",
        "I'm cantaring na torcida",
        "I'm batering palma no estádio",
        "I'm pediring VAR agora",
        "I'm xingaring o juiz",
        "I'm comemoraring de samba",
        "I'm entraring no bloco",
        "I'm pularing no carnaval",
        "I'm dançaring no trio",
        "I'm pediring mais glitter",
        "I'm fazering pose de malandro",
        "I'm pediring um cafezinho",
        "I'm marcaring reunião sem fim",
        "I'm falaring de trabalho remoto",
        "I'm dizering tá tudo bem",
        "I'm fingiring que entendeu",
        "I'm pediring um pastel",
        "I'm tomaring uma água",
        "I'm contaring uma fofoca",
        "I'm dizering você não sabe",
        "I'm mandaring áudio longo",
        "I'm respondering com figurinha",
        "I'm fazering cara de deboche",
        "I'm sairing dizendo valeu"
      ]
    }
  }
}
